runfalconpipelineintegration/__init__.py
runfalconpipelineintegration/__main__.py
runfalconpipelineintegration/int_main_module.py
runfalconpipelineintegration/model_credentials.py
runfalconpipelineintegration/model_execution_params.py
runfalconpipelineintegration/model_job.py
runfalconpipelineintegration/uc_authenticator.py
runfalconpipelineintegration/uc_scenario_runner.py
runfalconpipelineintegration/util_compliance_evaluator.py
runfalconpipelineintegration/util_configuration.py
runfalconpipelineintegration/util_http.py
runfalconpipelineintegration/util_http_client.py
runfalconpipelineintegration/util_json.py
runfalconpipelineintegration/util_logger.py
runfalcon_pipeline_integration-1.0.7.dist-info/LICENCE
runfalcon_pipeline_integration-1.0.7.dist-info/METADATA
runfalcon_pipeline_integration-1.0.7.dist-info/WHEEL
runfalcon_pipeline_integration-1.0.7.dist-info/top_level.txt
runfalcon_pipeline_integration-1.0.7.dist-info/RECORD
