Metadata-Version: 2.1
Name: runfalcon-pipeline-integration
Version: 1.0.7
Summary: Runfalcon tools to integrate with pipelines
Home-page: https://git-codecommit.zone.amazonaws.com/v1/repos/runfalcon-pipeline-integration-py-package
Author: Raul A. de Villa C.
Author-email: r@runfalcon.com
Classifier: Programming Language :: Python :: 3
Classifier: Operating System :: OS Independent
Requires-Python: >=3.6
License-File: LICENCE
Requires-Dist: requests
Requires-Dist: urllib3
